{
  "threat_type": "CIVILIAN_TRAFFIC",
  "duration": 3.0,
  "sample_rate": 16000,
  "environment": "maritime",
  "generated_at": "2025-09-22T11:11:05.703320",
  "audio_length": 48000,
  "peak_amplitude": 0.9,
  "rms_amplitude": 0.27197020856218335,
  "filename": "CIVILIAN_TRAFFIC_maritime_0088.wav",
  "file_path": "complete_27_class_military_collection/CIVILIAN_TRAFFIC_maritime_0088.wav",
  "quality_assessment": {
    "peak_amplitude": 0.8999999761581421,
    "rms_amplitude": 0.2719702124595642,
    "dynamic_range_db": 48.896526945580405,
    "snr_db": 0.6774189047299701,
    "thd_percent": 534.4278732631005
  },
  "sample_index": 88,
  "threat_category": "NON_THREAT",
  "priority_level": "LOW"
}