{
  "threat_type": "DIGGING_CONSTRUCTION",
  "duration": 3.0,
  "sample_rate": 16000,
  "environment": "mountain",
  "generated_at": "2025-09-22T11:11:34.180272",
  "audio_length": 48000,
  "peak_amplitude": 0.9,
  "rms_amplitude": 0.2166105410757003,
  "filename": "DIGGING_CONSTRUCTION_mountain_0059.wav",
  "file_path": "complete_27_class_military_collection/DIGGING_CONSTRUCTION_mountain_0059.wav",
  "quality_assessment": {
    "peak_amplitude": 0.8999999761581421,
    "rms_amplitude": 0.21661053597927094,
    "dynamic_range_db": 53.28244222357061,
    "snr_db": 0.17328058910722166,
    "thd_percent": 97.27624712858555
  },
  "sample_index": 59,
  "threat_category": "PERSONNEL_ACTIVITY",
  "priority_level": "MEDIUM"
}