{
  "threat_type": "DIGGING_CONSTRUCTION",
  "duration": 3.0,
  "sample_rate": 16000,
  "environment": "urban",
  "generated_at": "2025-09-22T11:11:33.996700",
  "audio_length": 48000,
  "peak_amplitude": 0.9,
  "rms_amplitude": 0.205780706591191,
  "filename": "DIGGING_CONSTRUCTION_urban_0031.wav",
  "file_path": "complete_27_class_military_collection/DIGGING_CONSTRUCTION_urban_0031.wav",
  "quality_assessment": {
    "peak_amplitude": 0.8999999761581421,
    "rms_amplitude": 0.20578069984912872,
    "dynamic_range_db": 52.64111906490249,
    "snr_db": 0.2227430681511611,
    "thd_percent": 274.8339645748635
  },
  "sample_index": 31,
  "threat_category": "PERSONNEL_ACTIVITY",
  "priority_level": "MEDIUM"
}