{
  "threat_type": "IFV_APC",
  "duration": 3.0,
  "sample_rate": 16000,
  "environment": "mountain",
  "generated_at": "2025-09-22T11:11:19.531572",
  "audio_length": 48000,
  "peak_amplitude": 0.9,
  "rms_amplitude": 0.24783185307958375,
  "filename": "IFV_APC_mountain_0134.wav",
  "file_path": "complete_27_class_military_collection/IFV_APC_mountain_0134.wav",
  "quality_assessment": {
    "peak_amplitude": 0.8999999761581421,
    "rms_amplitude": 0.24783186614513397,
    "dynamic_range_db": 52.96190356927589,
    "snr_db": 0.15100466830105694,
    "thd_percent": 42531.413658059304
  },
  "sample_index": 134,
  "threat_category": "DIRECT_COMBAT",
  "priority_level": "HIGH"
}