{
  "threat_type": "INCOMING_ARTILLERY",
  "duration": 3.0,
  "sample_rate": 16000,
  "environment": "urban",
  "generated_at": "2025-09-22T11:11:08.735848",
  "audio_length": 48000,
  "peak_amplitude": 0.9,
  "rms_amplitude": 0.21419945105977028,
  "filename": "INCOMING_ARTILLERY_urban_0101.wav",
  "file_path": "complete_27_class_military_collection/INCOMING_ARTILLERY_urban_0101.wav",
  "quality_assessment": {
    "peak_amplitude": 0.8999999761581421,
    "rms_amplitude": 0.21419943869113922,
    "dynamic_range_db": 50.059962169347145,
    "snr_db": 1.0671894221718334,
    "thd_percent": 76.67497095963813
  },
  "sample_index": 101,
  "threat_category": "IMMEDIATE_LETHAL",
  "priority_level": "CRITICAL"
}