{
  "threat_type": "INCOMING_ARTILLERY",
  "duration": 3.0,
  "sample_rate": 16000,
  "environment": "maritime",
  "generated_at": "2025-09-22T11:11:08.981345",
  "audio_length": 48000,
  "peak_amplitude": 0.9,
  "rms_amplitude": 0.20960196765203634,
  "filename": "INCOMING_ARTILLERY_maritime_0133.wav",
  "file_path": "complete_27_class_military_collection/INCOMING_ARTILLERY_maritime_0133.wav",
  "quality_assessment": {
    "peak_amplitude": 0.8999999761581421,
    "rms_amplitude": 0.2096019834280014,
    "dynamic_range_db": 50.1757166049898,
    "snr_db": 0.7870825206026173,
    "thd_percent": 76.15553737871632
  },
  "sample_index": 133,
  "threat_category": "IMMEDIATE_LETHAL",
  "priority_level": "CRITICAL"
}