{
  "threat_type": "PERSONNEL_VEHICLE",
  "duration": 3.0,
  "sample_rate": 16000,
  "environment": "maritime",
  "generated_at": "2025-09-22T11:11:33.480973",
  "audio_length": 48000,
  "peak_amplitude": 0.9,
  "rms_amplitude": 0.08851433461075997,
  "filename": "PERSONNEL_VEHICLE_maritime_0148.wav",
  "file_path": "complete_27_class_military_collection/PERSONNEL_VEHICLE_maritime_0148.wav",
  "quality_assessment": {
    "peak_amplitude": 0.8999999761581421,
    "rms_amplitude": 0.08851433545351028,
    "dynamic_range_db": 55.02693784861056,
    "snr_db": 0.36169547776249306,
    "thd_percent": 221.48946875591466
  },
  "sample_index": 148,
  "threat_category": "PERSONNEL_ACTIVITY",
  "priority_level": "MEDIUM"
}