{
  "threat_type": "PERSONNEL_VEHICLE",
  "duration": 3.0,
  "sample_rate": 16000,
  "environment": "mountain",
  "generated_at": "2025-09-22T11:11:33.665947",
  "audio_length": 48000,
  "peak_amplitude": 0.9,
  "rms_amplitude": 0.08703174723595626,
  "filename": "PERSONNEL_VEHICLE_mountain_0179.wav",
  "file_path": "complete_27_class_military_collection/PERSONNEL_VEHICLE_mountain_0179.wav",
  "quality_assessment": {
    "peak_amplitude": 0.8999999761581421,
    "rms_amplitude": 0.08703175187110901,
    "dynamic_range_db": 54.24230477651434,
    "snr_db": 0.39460653244356514,
    "thd_percent": 113.96947107629667
  },
  "sample_index": 179,
  "threat_category": "PERSONNEL_ACTIVITY",
  "priority_level": "MEDIUM"
}