{
  "threat_type": "RECON_AIRCRAFT",
  "duration": 3.0,
  "sample_rate": 16000,
  "environment": "desert",
  "generated_at": "2025-09-22T11:11:39.019159",
  "audio_length": 48000,
  "peak_amplitude": 0.9,
  "rms_amplitude": 0.3004052826779363,
  "filename": "RECON_AIRCRAFT_desert_0140.wav",
  "file_path": "complete_27_class_military_collection/RECON_AIRCRAFT_desert_0140.wav",
  "quality_assessment": {
    "peak_amplitude": 0.8999999761581421,
    "rms_amplitude": 0.3004052937030792,
    "dynamic_range_db": 48.01802993688415,
    "snr_db": 0.31034064792274557,
    "thd_percent": 11.330604168262319
  },
  "sample_index": 140,
  "threat_category": "SURVEILLANCE_RECON",
  "priority_level": "LOW_MEDIUM"
}