{
  "threat_type": "RECON_AIRCRAFT",
  "duration": 3.0,
  "sample_rate": 16000,
  "environment": "urban",
  "generated_at": "2025-09-22T11:11:39.382740",
  "audio_length": 48000,
  "peak_amplitude": 0.9,
  "rms_amplitude": 0.307290814140261,
  "filename": "RECON_AIRCRAFT_urban_0191.wav",
  "file_path": "complete_27_class_military_collection/RECON_AIRCRAFT_urban_0191.wav",
  "quality_assessment": {
    "peak_amplitude": 0.8999999761581421,
    "rms_amplitude": 0.30729082226753235,
    "dynamic_range_db": 48.52078412600311,
    "snr_db": 0.5843103308418826,
    "thd_percent": 10.028627709700135
  },
  "sample_index": 191,
  "threat_category": "SURVEILLANCE_RECON",
  "priority_level": "LOW_MEDIUM"
}