{
  "threat_type": "SURVEILLANCE_DRONE",
  "duration": 3.0,
  "sample_rate": 16000,
  "environment": "mountain",
  "generated_at": "2025-09-22T11:11:36.747696",
  "audio_length": 48000,
  "peak_amplitude": 0.9,
  "rms_amplitude": 0.3927203189064928,
  "filename": "SURVEILLANCE_DRONE_mountain_0014.wav",
  "file_path": "complete_27_class_military_collection/SURVEILLANCE_DRONE_mountain_0014.wav",
  "quality_assessment": {
    "peak_amplitude": 0.8999999761581421,
    "rms_amplitude": 0.3927203118801117,
    "dynamic_range_db": 48.96067997104198,
    "snr_db": 0.032170855359220936,
    "thd_percent": 4.266436346900117
  },
  "sample_index": 14,
  "threat_category": "SURVEILLANCE_RECON",
  "priority_level": "LOW_MEDIUM"
}