{
  "threat_type": "TANK_TRACKED",
  "duration": 3.0,
  "sample_rate": 16000,
  "environment": "maritime",
  "generated_at": "2025-09-22T11:11:17.107649",
  "audio_length": 48000,
  "peak_amplitude": 0.9,
  "rms_amplitude": 0.2170671963008219,
  "filename": "TANK_TRACKED_maritime_0038.wav",
  "file_path": "complete_27_class_military_collection/TANK_TRACKED_maritime_0038.wav",
  "quality_assessment": {
    "peak_amplitude": 0.8999999761581421,
    "rms_amplitude": 0.2170671969652176,
    "dynamic_range_db": 53.6084272468342,
    "snr_db": 0.22697397318274304,
    "thd_percent": 115.32203997339776
  },
  "sample_index": 38,
  "threat_category": "DIRECT_COMBAT",
  "priority_level": "HIGH"
}