{
  "threat_type": "TANK_TRACKED",
  "duration": 3.0,
  "sample_rate": 16000,
  "environment": "maritime",
  "generated_at": "2025-09-22T11:11:17.873179",
  "audio_length": 48000,
  "peak_amplitude": 0.9,
  "rms_amplitude": 0.22657380159364365,
  "filename": "TANK_TRACKED_maritime_0123.wav",
  "file_path": "complete_27_class_military_collection/TANK_TRACKED_maritime_0123.wav",
  "quality_assessment": {
    "peak_amplitude": 0.8999999761581421,
    "rms_amplitude": 0.22657380998134613,
    "dynamic_range_db": 53.60584855586438,
    "snr_db": 0.3116981549836576,
    "thd_percent": 221.70345660939995
  },
  "sample_index": 123,
  "threat_category": "DIRECT_COMBAT",
  "priority_level": "HIGH"
}