{
  "threat_type": "TANK_TRACKED",
  "duration": 3.0,
  "sample_rate": 16000,
  "environment": "maritime",
  "generated_at": "2025-09-22T11:11:18.111093",
  "audio_length": 48000,
  "peak_amplitude": 0.9,
  "rms_amplitude": 0.22856774279217118,
  "filename": "TANK_TRACKED_maritime_0153.wav",
  "file_path": "complete_27_class_military_collection/TANK_TRACKED_maritime_0153.wav",
  "quality_assessment": {
    "peak_amplitude": 0.8999999761581421,
    "rms_amplitude": 0.22856773436069489,
    "dynamic_range_db": 53.49839279774866,
    "snr_db": 0.2559914107451351,
    "thd_percent": 505.99511702533044
  },
  "sample_index": 153,
  "threat_category": "DIRECT_COMBAT",
  "priority_level": "HIGH"
}