{
  "threat_type": "TRANSPORT_AIRCRAFT",
  "duration": 3.0,
  "sample_rate": 16000,
  "environment": "urban",
  "generated_at": "2025-09-22T11:11:27.579223",
  "audio_length": 48000,
  "peak_amplitude": 0.9,
  "rms_amplitude": 0.3236657245274718,
  "filename": "TRANSPORT_AIRCRAFT_urban_0101.wav",
  "file_path": "complete_27_class_military_collection/TRANSPORT_AIRCRAFT_urban_0101.wav",
  "quality_assessment": {
    "peak_amplitude": 0.8999999761581421,
    "rms_amplitude": 0.32366570830345154,
    "dynamic_range_db": 51.531573770799156,
    "snr_db": 5.503588147297405,
    "thd_percent": 3.3377875009344242
  },
  "sample_index": 101,
  "threat_category": "LOGISTICS_TRANSPORT",
  "priority_level": "MEDIUM"
}